LICENSE
MANIFEST.in
README.md
helga_isup.py
requirements.txt
setup.py
helga_isup.egg-info/PKG-INFO
helga_isup.egg-info/SOURCES.txt
helga_isup.egg-info/dependency_links.txt
helga_isup.egg-info/entry_points.txt
helga_isup.egg-info/requires.txt
helga_isup.egg-info/top_level.txt