Metadata-Version: 1.1
Name: helga-isup
Version: 0.2.2
Summary: Helga plugin to check down for everyone or just me
Home-page: https://github.com/shaunduncan/helga-isup
Author: Shaun Duncan
Author-email: shaun.duncan@gmail.com
License: MIT
Keywords: helga isup down for everyone or just me
Platform: UNKNOWN
Classifier: Development Status :: 4 - Beta
Classifier: Topic :: Communications :: Chat :: Internet Relay Chat
Classifier: Framework :: Twisted
Classifier: License :: OSI Approved :: MIT License
Classifier: Operating System :: OS Independent
Classifier: Programming Language :: Python
Classifier: Programming Language :: Python :: 2
Classifier: Programming Language :: Python :: 2.6
Classifier: Programming Language :: Python :: 2.7
Classifier: Topic :: Software Development :: Libraries :: Python Modules
